arrowdantic-0.2.3.dist-info/METADATA
arrowdantic-0.2.3.dist-info/WHEEL
arrowdantic-0.2.3.dist-info/license_files/LICENSE
arrowdantic.libs/libltdl-3a30a669.so.7
arrowdantic.libs/libodbc-7462827c.so.2
arrowdantic/__init__.py
arrowdantic/arrowdantic.cpython-37m-x86_64-linux-gnu.so
arrowdantic-0.2.3.dist-info/RECORD
