Metadata-Version: 2.1
Name: arrowdantic
Version: 0.2.3
License-File: LICENSE
Summary: Arrow, pydantic style
Keywords: analytics,arrow,ODBC,parquet
Home-Page: https://github.com/jorgecarleitao/arrowdantic
Author: Jorge C. Leitao <jorgecarleitao@gmail.com>
Author-email: Jorge C. Leitao <jorgecarleitao@gmail.com>
License: Apache-2.0
Project-URL: Source Code, https://github.com/jorgecarleitao/arrowdantic
